leveled_hotbackup_s3_sync/__init__.py
leveled_hotbackup_s3_sync/__main__.py
leveled_hotbackup_s3_sync/app.py
leveled_hotbackup_s3_sync/config.py
leveled_hotbackup_s3_sync/erlang.py
leveled_hotbackup_s3_sync/hints.py
leveled_hotbackup_s3_sync/journal.py
leveled_hotbackup_s3_sync/manifest.py
leveled_hotbackup_s3_sync/retrieve.py
leveled_hotbackup_s3_sync/s3mmap.py
leveled_hotbackup_s3_sync/tests/app_test.py
leveled_hotbackup_s3_sync/tests/config_test.py
leveled_hotbackup_s3_sync/tests/erlang_test.py
leveled_hotbackup_s3_sync/tests/hints_test.py
leveled_hotbackup_s3_sync/tests/journal_test.py
leveled_hotbackup_s3_sync/tests/manifest_test.py
leveled_hotbackup_s3_sync/tests/retrieve_test.py
leveled_hotbackup_s3_sync/tests/s3mmap_test.py
leveled_hotbackup_s3_sync/tests/utils_test.py
leveled_hotbackup_s3_sync/utils.py
leveled_hotbackup_s3_sync-1.0.2.dist-info/LICENSE
leveled_hotbackup_s3_sync-1.0.2.dist-info/METADATA
leveled_hotbackup_s3_sync-1.0.2.dist-info/WHEEL
leveled_hotbackup_s3_sync-1.0.2.dist-info/entry_points.txt
leveled_hotbackup_s3_sync-1.0.2.dist-info/RECORD
