Metadata-Version: 2.1
Name: leveled-hotbackup-s3-sync
Version: 1.0.2
Summary: Tool to syncrhonise LevelEd hotbackup files to Amazon S3
Home-page: https://github.com/yorkshire-steve/leveled-hotbackup-s3-sync
License: Apache-2.0
Keywords: riak,leveled,backup,s3
Author: yorkshire-steve
Requires-Python: >=3.8,<4.0
Classifier: License :: OSI Approved :: Apache Software License
Classifier: Programming Language :: Python :: 3
Classifier: Programming Language :: Python :: 3.8
Classifier: Programming Language :: Python :: 3.9
Classifier: Programming Language :: Python :: 3.10
Classifier: Programming Language :: Python :: 3.11
Provides-Extra: retrieve
Requires-Dist: boto3 (==1.34.22)
Requires-Dist: frozendict (>=2.4.0,<3.0.0)
Requires-Dist: lz4 (>=4.3.3,<5.0.0) ; extra == "retrieve"
Requires-Dist: pure-cdb (>=4.0.0,<5.0.0)
Requires-Dist: s3fs (>=2023.12.2,<2024.0.0) ; extra == "retrieve"
Requires-Dist: tomli (>=2.0.1,<3.0.0) ; python_version < "3.11"
Project-URL: Repository, https://github.com/yorkshire-steve/leveled-hotbackup-s3-sync
